{"is_source_file": false, "format": "", "description": "", "external_files": [], "external_methods": [], "published": [], "classes": [], "methods": [], "calls": [], "search-terms": [], "state": 2, "file_id": 4, "knowledge_revision": 31, "git_revision": "1035de1690dfee811f352f555073edd204f53112", "hash": "17ea95571b9c097169bf2aa716038096", "format-version": 4, "code-base-name": "notes_frontend", "filename": "notes_frontend/index.html", "revision_history": [{"31": "1035de1690dfee811f352f555073edd204f53112"}]}