{"is_source_file": true, "format": "JavaScript", "description": "This file defines a React hook called useTizenKeys which adds a keydown event listener to handle Tizen remote control keys and calls corresponding handlers.", "external_files": [], "external_methods": ["useEffect"], "published": ["useTizenKeys"], "classes": [], "methods": [{"name": "useTizenKeys(handlers)", "description": "A React hook that registers keydown event listener to handle Tizen remote control keys and triggers callback handlers.", "scope": "", "scopeKind": ""}, {"name": "handleKeyDown(e)", "scope": "useTizenKeys", "scopeKind": "function", "description": "unavailable"}], "calls": ["window.addEventListener", "window.removeEventListener"], "search-terms": ["useTizenKeys", "Tizen", "remote control", "keyCodes", "React hooks"], "state": 2, "file_id": 9, "knowledge_revision": 23, "git_revision": "1035de1690dfee811f352f555073edd204f53112", "ctags": [{"_type": "tag", "name": "handleKeyDown", "path": "/home/kavia/workspace/code-generation/note-management-system-291466-291494/notes_frontend/src/hooks/useTizenKeys.js", "pattern": "/^    function handleKeyDown(e) {$/", "language": "JavaScript", "kind": "function", "signature": "(e)", "scope": "useTizenKeys", "scopeKind": "function"}, {"_type": "tag", "name": "useTizenKeys", "path": "/home/kavia/workspace/code-generation/note-management-system-291466-291494/notes_frontend/src/hooks/useTizenKeys.js", "pattern": "/^export function useTizenKeys(handlers) {$/", "language": "JavaScript", "kind": "function", "signature": "(handlers)"}], "hash": "5fc456686dc189c4465881ae78c0a489", "format-version": 4, "code-base-name": "notes_frontend", "filename": "notes_frontend/src/hooks/useTizenKeys.js", "revision_history": [{"23": "1035de1690dfee811f352f555073edd204f53112"}]}