{"is_source_file": false, "format": "", "description": "", "external_files": [], "external_methods": [], "published": [], "classes": [], "methods": [], "calls": [], "search-terms": [], "state": 2, "file_id": 5, "knowledge_revision": 56, "git_revision": "363bb4f891b9df22d05811d8d033f0d16623095d", "hash": "a9ebda20eb1364b9c83a687cbe6d5535", "format-version": 4, "code-base-name": "notes_frontend", "filename": "notes_frontend/README.md", "revision_history": [{"56": "363bb4f891b9df22d05811d8d033f0d16623095d"}]}